mcraft/__init__.py
mcraft/craft.py
mcraft/craft_utils.py
mcraft/file_utils.py
mcraft/imgproc.py
mcraft/networks.py
mcraft/refinenet.py
mcraft/test.py
mcraft/utils.py
mcraft/basenet/__init__.py
mcraft/basenet/vgg16_bn.py
mcraft-0.0.3.dist-info/LICENSE
mcraft-0.0.3.dist-info/METADATA
mcraft-0.0.3.dist-info/WHEEL
mcraft-0.0.3.dist-info/top_level.txt
mcraft-0.0.3.dist-info/RECORD
