Metadata-Version: 2.1
Name: mcraft
Version: 0.0.3
Summary: A modern version of CRAFT-pytorch using the latest versions
Home-page: https://github.com/manbehindthemadness/modern-craft
Author: Manbehindthemadness
Author-email: manbehindthemadness@gmail.com
Classifier: Programming Language :: Python :: 3
Classifier: License :: OSI Approved :: MIT License
Classifier: Operating System :: OS Independent
Requires-Python: >=3.10
License-File: LICENSE
Requires-Dist: scikit-image >=0.14.2
Requires-Dist: scipy >=1.1.0
Requires-Dist: numpy
Requires-Dist: opencv-python >=3.4.2.17
Requires-Dist: torch >=2.0.0
Requires-Dist: torchvision >=0.17.0
Requires-Dist: quickdl
